uu2nano.py
uu2nano-1.0.dist-info/METADATA
uu2nano-1.0.dist-info/WHEEL
uu2nano-1.0.dist-info/top_level.txt
uu2nano-1.0.dist-info/RECORD
