Metadata-Version: 2.1
Name: uu2nano
Version: 1.0
Summary: Conversion tool from UUID to nanoid and vice versa
Author-email: Aleksandr Karpinskii <homm86@gmail.com>
Project-URL: Repository, https://github.com/homm/uu2nano
Keywords: uuid,nanoid
Requires-Python: >=3.7
